query_maker/MySql.py
query_maker/QueryMaker.py
query_maker/__init__.py
query_maker/table.py
tests/__init__.py
tests/alchemy.py
query_maker_ryazantseff-0.3.7.dist-info/LICENSE
query_maker_ryazantseff-0.3.7.dist-info/METADATA
query_maker_ryazantseff-0.3.7.dist-info/WHEEL
query_maker_ryazantseff-0.3.7.dist-info/top_level.txt
query_maker_ryazantseff-0.3.7.dist-info/RECORD
