Metadata-Version: 2.1
Name: query-maker-ryazantseff
Version: 0.3.7
Summary: MySql query builder and executor, based on aiomysql
Home-page: https://github.com/ryazantseff/mysql-querymaker
Author: Maxim Ryazantsev
Author-email: maxim.ryazancev@gmail.com
License: MIT
Keywords: Mysql,Sql,Query,async
Platform: UNKNOWN
Classifier: Development Status :: 3 - Alpha
Classifier: Intended Audience :: Developers
Classifier: Topic :: Software Development :: Build Tools
Classifier: License :: OSI Approved :: MIT License
Classifier: Programming Language :: Python :: 3.8
Classifier: Programming Language :: Python :: 3.9
Requires-Dist: asyncio
Requires-Dist: aiomysql
Requires-Dist: sqlalchemy (==1.3.24)
Requires-Dist: pandas
